npdk/__init__.py
npdk/core.py
npdk/exceptions.py
npdk/protocol/__init__.py
npdk/protocol/icmp.py
npdk-0.0.2.dist-info/LICENSE
npdk-0.0.2.dist-info/METADATA
npdk-0.0.2.dist-info/WHEEL
npdk-0.0.2.dist-info/top_level.txt
npdk-0.0.2.dist-info/RECORD
